Workbook

Sheet 1_Inputs
A1: Simulation de Monte Carlo – Projet d'investissement (VAN sur 5 ans)
A3: Hypothèses principales
A4: Investissement initial (t=0) – montant positif | B4: 1000000 | C4: ⬅ à modifier
A5: Discount rate (r) | B5: 0.12 | C5: ⬅ à modifier
A6: Nombre d'itérations (Monte Carlo) | B6: 250 | C6: ⬅ à modifier
A8: Hypothèses de cash flows (fin d'année) – incertitude par année
A9: Année | B9: Cash flow espéré | C9: Volatilité (σ %) | D9: Écart-type (σ) | E9: Note
A10: 1 | B10: 250000 | C10: 0.8 | D10: =B10*C10 -> 200000 | E10: On applique un choc commun Z (corrélé sur 5 ans)
A11: 2 | B11: 300000 | C11: 0.2 | D11: =B11*C11 -> 60000 | E11: On applique un choc commun Z (corrélé sur 5 ans)
A12: 3 | B12: 350000 | C12: 0.18 | D12: =B12*C12 -> 63000 | E12: On applique un choc commun Z (corrélé sur 5 ans)
A13: 4 | B13: 400000 | C13: 0.18 | D13: =B13*C13 -> 72000 | E13: On applique un choc commun Z (corrélé sur 5 ans)
A14: 5 | B14: 450000 | C14: 0.25 | D14: =B14*C14 -> 112500 | E14: On applique un choc commun Z (corrélé sur 5 ans)
A16: Idée du modèle (simple et clair)
A17: On tire un choc unique Z ~ N(0,1) par scénario : Z = NORM.INV(RAND(),0,1)
A18: Puis CF_t = MAX(0 ; CF_espéré_t × (1 + σ_t × Z)) → CFs corrélés

Sheet 2_Simulation
A1: Simulation Monte Carlo (recalculer: F9) – CF corrélés via un choc commun Z
A2: Itération | B2: Choc Z (N(0,1)) | C2: CF Année 1 | D2: CF Année 2 | E2: CF Année 3 | F2: CF Année 4 | G2: CF Année 5 | H2: VAN (NPV) | I2: Décision
A3: 1 | B3: =NORMINV(RAND(),0,1) -> -1.3784188 | C3: =MAX(0,'1_Inputs'!$B$10*(1+'1_Inputs'!$C$10*$B3)) -> 0 | D3: =MAX(0,'1_Inputs'!$B$11*(1+'1_Inputs'!$C$11*$B3)) -> 217294.87 | E3: =MAX(0,'1_Inputs'!$B$12*(1+'1_Inputs'!$C$12*$B3)) -> 263159.62 | F3: =MAX(0,'1_Inputs'!$B$13*(1+'1_Inputs'!$C$13*$B3)) -> 300753.85 | G3: =MAX(0,'1_Inputs'!$B$14*(1+'1_Inputs'!$C$14*$B3)) -> 294927.88 | H3: =NPV('1_Inputs'!$B$5,C3:G3)-'1_Inputs'!$B$4 -> -280977.53 | I3: =IF(H3>0,"VAN>0","VAN<0") -> VAN<0
A4: 2 | B4: =NORMINV(RAND(),0,1) -> 0.22777811 | C4: =MAX(0,'1_Inputs'!$B$10*(1+'1_Inputs'!$C$10*$B4)) -> 295555.62 | D4: =MAX(0,'1_Inputs'!$B$11*(1+'1_Inputs'!$C$11*$B4)) -> 313666.69 | E4: =MAX(0,'1_Inputs'!$B$12*(1+'1_Inputs'!$C$12*$B4)) -> 364350.02 | F4: =MAX(0,'1_Inputs'!$B$13*(1+'1_Inputs'!$C$13*$B4)) -> 416400.02 | G4: =MAX(0,'1_Inputs'!$B$14*(1+'1_Inputs'!$C$14*$B4)) -> 475625.04 | H4: =NPV('1_Inputs'!$B$5,C4:G4)-'1_Inputs'!$B$4 -> 307791.42 | I4: =IF(H4>0,"VAN>0","VAN<0") -> VAN>0
A5: 3 | B5: =NORMINV(RAND(),0,1) -> 0.85141618 | C5: =MAX(0,'1_Inputs'!$B$10*(1+'1_Inputs'!$C$10*$B5)) -> 420283.24 | D5: =MAX(0,'1_Inputs'!$B$11*(1+'1_Inputs'!$C$11*$B5)) -> 351084.97 | E5: =MAX(0,'1_Inputs'!$B$12*(1+'1_Inputs'!$C$12*$B5)) -> 403639.22 | F5: =MAX(0,'1_Inputs'!$B$13*(1+'1_Inputs'!$C$13*$B5)) -> 461301.97 | G5: =MAX(0,'1_Inputs'!$B$14*(1+'1_Inputs'!$C$14*$B5)) -> 545784.32 | H5: =NPV('1_Inputs'!$B$5,C5:G5)-'1_Inputs'!$B$4 -> 545296.52 | I5: =IF(H5>0,"VAN>0","VAN<0") -> VAN>0
A6: 4 | B6: =NORMINV(RAND(),0,1) -> 2.0330826 | C6: =MAX(0,'1_Inputs'!$B$10*(1+'1_Inputs'!$C$10*$B6)) -> 656616.52 | D6: =MAX(0,'1_Inputs'!$B$11*(1+'1_Inputs'!$C$11*$B6)) -> 421984.96 | E6: =MAX(0,'1_Inputs'!$B$12*(1+'1_Inputs'!$C$12*$B6)) -> 478084.2 | F6: =MAX(0,'1_Inputs'!$B$13*(1+'1_Inputs'!$C$13*$B6)) -> 546381.95 | G6: =MAX(0,'1_Inputs'!$B$14*(1+'1_Inputs'!$C$14*$B6)) -> 678721.79 | H6: =NPV('1_Inputs'!$B$5,C6:G6)-'1_Inputs'!$B$4 -> 995320.05 | I6: =IF(H6>0,"VAN>0","VAN<0") -> VAN>0
A7: 5 | B7: =NORMINV(RAND(),0,1) -> -0.040398445 | C7: =MAX(0,'1_Inputs'!$B$10*(1+'1_Inputs'!$C$10*$B7)) -> 241920.31 | D7: =MAX(0,'1_Inputs'!$B$11*(1+'1_Inputs'!$C$11*$B7)) -> 297576.09 | E7: =MAX(0,'1_Inputs'!$B$12*(1+'1_Inputs'!$C$12*$B7)) -> 347454.9 | F7: =MAX(0,'1_Inputs'!$B$13*(1+'1_Inputs'!$C$13*$B7)) -> 397091.31 | G7: =MAX(0,'1_Inputs'!$B$14*(1+'1_Inputs'!$C$14*$B7)) -> 445455.17 | H7: =NPV('1_Inputs'!$B$5,C7:G7)-'1_Inputs'!$B$4 -> 205659.59 | I7: =IF(H7>0,"VAN>0","VAN<0") -> VAN>0
A8: 6 | B8: =NORMINV(RAND(),0,1) -> 0.94224954 | C8: =MAX(0,'1_Inputs'!$B$10*(1+'1_Inputs'!$C$10*$B8)) -> 438449.91 | D8: =MAX(0,'1_Inputs'!$B$11*(1+'1_Inputs'!$C$11*$B8)) -> 356534.97 | E8: =MAX(0,'1_Inputs'!$B$12*(1+'1_Inputs'!$C$12*$B8)) -> 409361.72 | F8: =MAX(0,'1_Inputs'!$B$13*(1+'1_Inputs'!$C$13*$B8)) -> 467841.97 | G8: =MAX(0,'1_Inputs'!$B$14*(1+'1_Inputs'!$C$14*$B8)) -> 556003.07 | H8: =NPV('1_Inputs'!$B$5,C8:G8)-'1_Inputs'!$B$4 -> 579889.32 | I8: =IF(H8>0,"VAN>0","VAN<0") -> VAN>0
A9: 7 | B9: =NORMINV(RAND(),0,1) -> 1.5657596 | C9: =MAX(0,'1_Inputs'!$B$10*(1+'1_Inputs'!$C$10*$B9)) -> 563151.93 | D9: =MAX(0,'1_Inputs'!$B$11*(1+'1_Inputs'!$C$11*$B9)) -> 393945.58 | E9: =MAX(0,'1_Inputs'!$B$12*(1+'1_Inputs'!$C$12*$B9)) -> 448642.86 | F9: =MAX(0,'1_Inputs'!$B$13*(1+'1_Inputs'!$C$13*$B9)) -> 512734.69 | G9: =MAX(0,'1_Inputs'!$B$14*(1+'1_Inputs'!$C$14*$B9)) -> 626147.96 | H9: =NPV('1_Inputs'!$B$5,C9:G9)-'1_Inputs'!$B$4 -> 817345.68 | I9: =IF(H9>0,"VAN>0","VAN<0") -> VAN>0
A10: 8 | B10: =NORMINV(RAND(),0,1) -> 0.1147418 | C10: =MAX(0,'1_Inputs'!$B$10*(1+'1_Inputs'!$C$10*$B10)) -> 272948.36 | D10: =MAX(0,'1_Inputs'!$B$11*(1+'1_Inputs'!$C$11*$B10)) -> 306884.51 | E10: =MAX(0,'1_Inputs'!$B$12*(1+'1_Inputs'!$C$12*$B10)) -> 357228.73 | F10: =MAX(0,'1_Inputs'!$B$13*(1+'1_Inputs'!$C$13*$B10)) -> 408261.41 | G10: =MAX(0,'1_Inputs'!$B$14*(1+'1_Inputs'!$C$14*$B10)) -> 462908.45 | H10: =NPV('1_Inputs'!$B$5,C10:G10)-'1_Inputs'!$B$4 -> 264742.9 | I10: =IF(H10>0,"VAN>0","VAN<0") -> VAN>0
A11: 9 | B11: =NORMINV(RAND(),0,1) -> -1.2815955 | C11: =MAX(0,'1_Inputs'!$B$10*(1+'1_Inputs'!$C$10*$B11)) -> 0 | D11: =MAX(0,'1_Inputs'!$B$11*(1+'1_Inputs'!$C$11*$B11)) -> 223104.27 | E11: =MAX(0,'1_Inputs'!$B$12*(1+'1_Inputs'!$C$12*$B11)) -> 269259.48 | F11: =MAX(0,'1_Inputs'!$B$13*(1+'1_Inputs'!$C$13*$B11)) -> 307725.13 | G11: =MAX(0,'1_Inputs'!$B$14*(1+'1_Inputs'!$C$14*$B11)) -> 305820.51 | H11: =NPV('1_Inputs'!$B$5,C11:G11)-'1_Inputs'!$B$4 -> -261393.41 | I11: =IF(H11>0,"VAN>0","VAN<0") -> VAN<0
A12: 10 | B12: =NORMINV(RAND(),0,1) -> 0.44826388 | C12: =MAX(0,'1_Inputs'!$B$10*(1+'1_Inputs'!$C$10*$B12)) -> 339652.78 | D12: =MAX(0,'1_Inputs'!$B$11*(1+'1_Inputs'!$C$11*$B12)) -> 326895.83 | E12: =MAX(0,'1_Inputs'!$B$12*(1+'1_Inputs'!$C$12*$B12)) -> 378240.62 | F12: =MAX(0,'1_Inputs'!$B$13*(1+'1_Inputs'!$C$13*$B12)) -> 432275 | G12: =MAX(0,'1_Inputs'!$B$14*(1+'1_Inputs'!$C$14*$B12)) -> 500429.69 | H12: =NPV('1_Inputs'!$B$5,C12:G12)-'1_Inputs'!$B$4 -> 391760.79 | I12: =IF(H12>0,"VAN>0","VAN<0") -> VAN>0
A13: 11 | B13: =NORMINV(RAND(),0,1) -> -0.41441901 | C13: =MAX(0,'1_Inputs'!$B$10*(1+'1_Inputs'!$C$10*$B13)) -> 167116.2 | D13: =MAX(0,'1_Inputs'!$B$11*(1+'1_Inputs'!$C$11*$B13)) -> 275134.86 | E13: =MAX(0,'1_Inputs'!$B$12*(1+'1_Inputs'!$C$12*$B13)) -> 323891.6 | F13: =MAX(0,'1_Inputs'!$B$13*(1+'1_Inputs'!$C$13*$B13)) -> 370161.83 | G13: =MAX(0,'1_Inputs'!$B$14*(1+'1_Inputs'!$C$14*$B13)) -> 403377.86 | H13: =NPV('1_Inputs'!$B$5,C13:G13)-'1_Inputs'!$B$4 -> 63218.33 | I13: =IF(H13>0,"VAN>0","VAN<0") -> VAN>0
A14: 12 | B14: =NORMINV(RAND(),0,1) -> -0.31658597 | C14: =MAX(0,'1_Inputs'!$B$10*(1+'1_Inputs'!$C$10*$B14)) -> 186682.81 | D14: =MAX(0,'1_Inputs'!$B$11*(1+'1_Inputs'!$C$11*$B14)) -> 281004.84 | E14: =MAX(0,'1_Inputs'!$B$12*(1+'1_Inputs'!$C$12*$B14)) -> 330055.08 | F14: =MAX(0,'1_Inputs'!$B$13*(1+'1_Inputs'!$C$13*$B14)) -> 377205.81 | G14: =MAX(0,'1_Inputs'!$B$14*(1+'1_Inputs'!$C$14*$B14)) -> 414384.08 | H14: =NPV('1_Inputs'!$B$5,C14:G14)-'1_Inputs'!$B$4 -> 100476.87 | I14: =IF(H14>0,"VAN>0","VAN<0") -> VAN>0
... A202: 200 | B202: =NORMINV(RAND(),0,1) -> 0.29574929 | C202: =MAX(0,'1_Inputs'!$B$10*(1+'1_Inputs'!$C$10*$B202)) -> 309149.86 | D202: =MAX(0,'1_Inputs'!$B$11*(1+'1_Inputs'!$C$11*$B202)) -> 317744.96 | E202: =MAX(0,'1_Inputs'!$B$12*(1+'1_Inputs'!$C$12*$B202)) -> 368632.21 | F202: =MAX(0,'1_Inputs'!$B$13*(1+'1_Inputs'!$C$13*$B202)) -> 421293.95 | G202: =MAX(0,'1_Inputs'!$B$14*(1+'1_Inputs'!$C$14*$B202)) -> 483271.79 | H202: =NPV('1_Inputs'!$B$5,C202:G202)-'1_Inputs'!$B$4 -> 333677.43 | I202: =IF(H202>0,"VAN>0","VAN<0") -> VAN>0

Sheet 3_Results
A1: Résultats – VAN (NPV) simulée
A3: Statistiques clés (sur la colonne VAN de 2_Simulation) | D3: Histogramme (répartition de la VAN)
A4: VAN moyenne | B4: =AVERAGE('2_Simulation'!$H$3:$H$202) -> 233537.82 | D4: Borne inf. | E4: Borne sup. | F4: Fréquence
A5: Médiane | B5: =MEDIAN('2_Simulation'!$H$3:$H$202) -> 227513.13 | D5: -800000 | E5: -700000 | F5: =COUNTIFS('2_Simulation'!$H$3:$H$202,">="&D5,'2_Simulation'!$H$3:$H$202,"<"&E5) -> 0
A6: Écart-type | B6: =_xlfn.STDEV.P('2_Simulation'!$H$3:$H$202) -> 352690.08 | D6: -700000 | E6: -600000 | F6: =COUNTIFS('2_Simulation'!$H$3:$H$202,">="&D6,'2_Simulation'!$H$3:$H$202,"<"&E6) -> 0
A7: 5e percentile (approx. via SMALL) | B7: =SMALL('2_Simulation'!$H$3:$H$202,MAX(1,ROUNDUP(0.05*COUNT('2_Simulation'!$H$3:$H$202),0))) -> -349169.48 | D7: -600000 | E7: -500000 | F7: =COUNTIFS('2_Simulation'!$H$3:$H$202,">="&D7,'2_Simulation'!$H$3:$H$202,"<"&E7) -> 2
A8: 95e percentile (approx. via LARGE) | B8: =LARGE('2_Simulation'!$H$3:$H$202,MAX(1,ROUNDUP(0.05*COUNT('2_Simulation'!$H$3:$H$202),0))) -> 832206.86 | D8: -500000 | E8: -400000 | F8: =COUNTIFS('2_Simulation'!$H$3:$H$202,">="&D8,'2_Simulation'!$H$3:$H$202,"<"&E8) -> 3
A9: Probabilité VAN > 0 | B9: =COUNTIF('2_Simulation'!$H$3:$H$202,">0")/COUNT('2_Simulation'!$H$3:$H$202) -> 0.725 | D9: -400000 | E9: -300000 | F9: =COUNTIFS('2_Simulation'!$H$3:$H$202,">="&D9,'2_Simulation'!$H$3:$H$202,"<"&E9) -> 7
A10: Minimum | B10: =MIN('2_Simulation'!$H$3:$H$202) -> -559212.61 | D10: -300000 | E10: -200000 | F10: =COUNTIFS('2_Simulation'!$H$3:$H$202,">="&D10,'2_Simulation'!$H$3:$H$202,"<"&E10) -> 15
A11: Maximum | B11: =MAX('2_Simulation'!$H$3:$H$202) -> 1179825.1 | D11: -200000 | E11: -100000 | F11: =COUNTIFS('2_Simulation'!$H$3:$H$202,">="&D11,'2_Simulation'!$H$3:$H$202,"<"&E11) -> 13
A12: Nombre d'itérations | B12: ='1_Inputs'!$B$6 -> 250 | D12: -100000 | E12: 0 | F12: =COUNTIFS('2_Simulation'!$H$3:$H$202,">="&D12,'2_Simulation'!$H$3:$H$202,"<"&E12) -> 15
D13: 0 | E13: 100000 | F13: =COUNTIFS('2_Simulation'!$H$3:$H$202,">="&D13,'2_Simulation'!$H$3:$H$202,"<"&E13) -> 13
D14: 100000 | E14: 200000 | F14: =COUNTIFS('2_Simulation'!$H$3:$H$202,">="&D14,'2_Simulation'!$H$3:$H$202,"<"&E14) -> 24
A15: Comment lire ces résultats ? | D15: 200000 | E15: 300000 | F15: =COUNTIFS('2_Simulation'!$H$3:$H$202,">="&D15,'2_Simulation'!$H$3:$H$202,"<"&E15) -> 25
A16: • VAN moyenne > 0 : rentable en moyenne. • Probabilité VAN>0 : % des scénarios créateurs de valeur. • 5e percentile : approximation de la queue défavorable. • 95e percentile : approximation de la queue favorable. | D16: 300000 | E16: 400000 | F16: =COUNTIFS('2_Simulation'!$H$3:$H$202,">="&D16,'2_Simulation'!$H$3:$H$202,"<"&E16) -> 21
D17: 400000 | E17: 500000 | F17: =COUNTIFS('2_Simulation'!$H$3:$H$202,">="&D17,'2_Simulation'!$H$3:$H$202,"<"&E17) -> 18
D18: 500000 | E18: 600000 | F18: =COUNTIFS('2_Simulation'!$H$3:$H$202,">="&D18,'2_Simulation'!$H$3:$H$202,"<"&E18) -> 15
D19: 600000 | E19: 700000 | F19: =COUNTIFS('2_Simulation'!$H$3:$H$202,">="&D19,'2_Simulation'!$H$3:$H$202,"<"&E19) -> 10
D20: 700000 | E20: 800000 | F20: =COUNTIFS('2_Simulation'!$H$3:$H$202,">="&D20,'2_Simulation'!$H$3:$H$202,"<"&E20) -> 8
D21: 800000 | E21: 900000 | F21: =COUNTIFS('2_Simulation'!$H$3:$H$202,">="&D21,'2_Simulation'!$H$3:$H$202,"<"&E21) -> 3
D22: 900000 | E22: 1000000 | F22: =COUNTIFS('2_Simulation'!$H$3:$H$202,">="&D22,'2_Simulation'!$H$3:$H$202,"<"&E22) -> 4
D23: 1000000 | E23: 1100000 | F23: =COUNTIFS('2_Simulation'!$H$3:$H$202,">="&D23,'2_Simulation'!$H$3:$H$202,"<"&E23) -> 2
D24: 1100000 | E24: 1200000 | F24: =COUNTIFS('2_Simulation'!$H$3:$H$202,">="&D24,'2_Simulation'!$H$3:$H$202,"<"&E24) -> 2
D25: 1200000 | F25: =COUNTIF('2_Simulation'!$H$3:$H$202,">="&D25) -> 0

Sheet 4_Mode_d'emploi
A1: Mode d'emploi (rapide)
A3: 1) Onglet 1_Inputs : modifie en bleu l’investissement initial, le discount rate (10% ici), les cash flows espérés et la volatilité.
A4: 2) Onglet 2_Simulation : chaque ligne = 1 scénario. On tire un choc commun Z = NORM.INV(RAND(),0,1) puis on perturbe tous les cash flows.
A5: 3) Appuie sur F9 (ou Formules > Calculer maintenant) pour relancer la simulation.
A6: 4) Onglet 3_Results : lis les stats (moyenne, quantiles approx., P(VAN>0)) et l’histogramme.
A8: Pourquoi un seul choc Z ? Modèle très simple qui crée des cash flows corrélés (bon marché → bons CF sur plusieurs années).
A9: Pour un modèle plus riche : utilise 1 RAND() par année (indépendant), ou ajoute un second choc (tendance).
